stockstui/__init__.py
stockstui/common.py
stockstui/config_manager.py
stockstui/log_handler.py
stockstui/main.css
stockstui/main.py
stockstui/parser.py
stockstui/data_providers/__init__.py
stockstui/data_providers/fred_provider.py
stockstui/data_providers/market_provider.py
stockstui/data_providers/options_provider.py
stockstui/data_providers/portfolio.py
stockstui/database/__init__.py
stockstui/database/db_manager.py
stockstui/default_configs/lists.json
stockstui/default_configs/portfolios.json
stockstui/default_configs/settings.json
stockstui/default_configs/themes.json
stockstui/documents/help.txt
stockstui/presentation/__init__.py
stockstui/presentation/formatter.py
stockstui/ui/__init__.py
stockstui/ui/edit_fred_series_modal.py
stockstui/ui/modals.py
stockstui/ui/position_modal.py
stockstui/ui/quick_edit_ticker_modal.py
stockstui/ui/suggesters.py
stockstui/ui/views/__init__.py
stockstui/ui/views/config_view.py
stockstui/ui/views/debug_view.py
stockstui/ui/views/fred_view.py
stockstui/ui/views/history_view.py
stockstui/ui/views/news_view.py
stockstui/ui/views/options_view.py
stockstui/ui/views/config_views/__init__.py
stockstui/ui/views/config_views/fred_config_view.py
stockstui/ui/views/config_views/general_config_view.py
stockstui/ui/views/config_views/lists_config_view.py
stockstui/ui/views/config_views/main_config_view.py
stockstui/ui/views/config_views/portfolio_config_view.py
stockstui/ui/widgets/__init__.py
stockstui/ui/widgets/history_chart.py
stockstui/ui/widgets/navigable_data_table.py
stockstui/ui/widgets/oi_chart.py
stockstui/ui/widgets/search_box.py
stockstui/ui/widgets/tag_filter.py
stockstui/ui/widgets/vim_radio_set.py
stockstui/utils/__init__.py
stockstui/utils/black_scholes.py
stockstui-0.1.0b12.dist-info/licenses/LICENSE
stockstui-0.1.0b12.dist-info/METADATA
stockstui-0.1.0b12.dist-info/WHEEL
stockstui-0.1.0b12.dist-info/entry_points.txt
stockstui-0.1.0b12.dist-info/top_level.txt
stockstui-0.1.0b12.dist-info/RECORD
