Metadata-Version: 2.4
Name: stocksTUI
Version: 0.1.0b12
Summary: A stylish and feature-rich Terminal User Interface for monitoring stock prices, news, and historical data.
Author-email: Andriy <project-git@techie.com>
License-Expression: GPL-3.0-or-later
Project-URL: Homepage, https://github.com/andriy-git/stocksTUI
Project-URL: Bug Tracker, https://github.com/andriy-git/stocksTUI/issues
Keywords: tui,stocks,finance,terminal,textual,yfinance
Classifier: Development Status :: 4 - Beta
Classifier: Environment :: Console
Classifier: Intended Audience :: End Users/Desktop
Classifier: Operating System :: MacOS
Classifier: Operating System :: POSIX :: Linux
Classifier: Operating System :: Microsoft :: Windows
Classifier: Programming Language :: Python :: 3
Classifier: Programming Language :: Python :: 3.10
Classifier: Programming Language :: Python :: 3.11
Classifier: Programming Language :: Python :: 3.12
Classifier: Programming Language :: Python :: 3.13
Classifier: Programming Language :: Python :: 3.14
Classifier: Topic :: Office/Business :: Financial :: Investment
Requires-Python: >=3.10
License-File: LICENSE
Requires-Dist: textual~=5.3.0
Requires-Dist: yfinance>=0.2.65
Requires-Dist: pandas_market_calendars~=5.1.1
Requires-Dist: plotext~=5.3.2
Requires-Dist: textual-plotext~=1.0.1
Requires-Dist: pandas~=2.3.0
Requires-Dist: requests
Requires-Dist: python-dateutil
Provides-Extra: dev
Requires-Dist: ruff; extra == "dev"
Requires-Dist: mypy; extra == "dev"
Requires-Dist: coverage; extra == "dev"
Requires-Dist: hypothesis; extra == "dev"
Requires-Dist: pydantic; extra == "dev"
Requires-Dist: mutmut; extra == "dev"
Dynamic: license-file
